[
  {
    "key": "dashboard",
    "label": "Dashboard",
    "icon": "FaHome",
    "link": "/"
  },
  {
    "key": "userManagement",
    "label": "Parents Management",
    "icon": "FiUser",
    "link": "/dashboard/parentsManagement"
  },
  {
    "key": "tutorManagement",
    "label": "Tutor Management",
    "icon": "FiUser",
    "link": "/dashboard/tutorManagement"
  },
   {
    "key": "childManagement",
    "label": "Child Management",
    "icon": "FiUser",
    "link": "/dashboard/childManagement"
  },
  {
    "key": "conultManagement",
    "label": "Consult Management",
    "icon": "FiUser",
    "link": "/dashboard/consultManagement"
  },
  {
    "key": "tutionManagement",
    "label": "Tution Management",
    "icon": "FiUser",
    "link": "/dashboard/tutionManagement"
  },
  {
    "key": "adminManage",
    "label": "Admin Management",
    "icon": "FiUser",
    "link": "/dashboard/adminManage"
  },
   {
    "key": "blogManagement",
    "label": "Blog Management",
    "icon": "FiUser",
    "link": "/dashboard/blogManagement"
  },
  {
    "key": "videoCreatorManagement",
    "label": "Video Management",
    "icon": "FiUser",
    "link": "/dashboard/videoCreatorManagement"
  },
   
  {
    "key": "banerManagement",
    "label": "baner Management",
    "icon": "FiUser",
    "link": "/dashboard/bannerManagement"
  },

  
  {
    "key": "settings",
    "label": "Settings",
    "icon": "IoSettingsOutline",
    "link": "/dashboard/Settings/profile",
    "children": [
      {
        "key": "profile",
        "label": "Profile",
        "link": "/dashboard/Settings/profile"
      },
      {
        "key": "terms",
        "label": "Terms & Condition",
        "link": "/dashboard/Settings/Terms&Condition"
      },
      {
        "key": "privacy",
        "label": "Privacy Policy",
        "link": "/dashboard/Settings/PrivacyPolicy"
      },
      {
        "key": "faq",
        "label": "FAQ",
        "link": "/dashboard/Settings/FAQ"
      },
      {
        "key": "about",
        "label": "About Us",
        "link": "/dashboard/Settings/aboutUs"
      }
    ]
  }
]
